integrations/__init__.py
integrations/bridge_between_zulips/README.md
integrations/bridge_between_zulips/interrealm_bridge_config.py
integrations/bridge_between_zulips/run-interrealm-bridge
integrations/bridge_with_irc/README.md
integrations/bridge_with_irc/irc-mirror.py
integrations/bridge_with_irc/irc_mirror_backend.py
integrations/bridge_with_irc/requirements.txt
integrations/bridge_with_matrix/README.md
integrations/bridge_with_matrix/__init__.py
integrations/bridge_with_matrix/matrix_bridge.py
integrations/bridge_with_matrix/requirements.txt
integrations/bridge_with_matrix/test_matrix.py
integrations/bridge_with_slack/README.md
integrations/bridge_with_slack/bridge_with_slack_config.py
integrations/bridge_with_slack/requirements.txt
integrations/bridge_with_slack/run-slack-bridge
integrations/codebase/requirements.txt
integrations/codebase/zulip_codebase_config.py
integrations/codebase/zulip_codebase_mirror
integrations/git/post-receive
integrations/git/requirements.txt
integrations/git/zulip_git_config.py
integrations/google/get-google-credentials
integrations/google/google-calendar
integrations/google/requirements.txt
integrations/hg/requirements.txt
integrations/hg/zulip_changegroup.py
integrations/jabber/jabber_mirror.py
integrations/jabber/jabber_mirror_backend.py
integrations/jabber/requirements.txt
integrations/jira/requirements.txt
integrations/jira/org/humbug/jira/ZulipListener.groovy
integrations/log2zulip/log2zulip
integrations/log2zulip/requirements.txt
integrations/nagios/nagios-notify-zulip
integrations/nagios/requirements.txt
integrations/nagios/zulip_nagios.cfg
integrations/nagios/zuliprc.example
integrations/openshift/post_deploy
integrations/openshift/requirements.txt
integrations/openshift/zulip_openshift_config.py
integrations/perforce/git_p4.py
integrations/perforce/license.txt
integrations/perforce/requirements.txt
integrations/perforce/zulip_change-commit.py
integrations/perforce/zulip_perforce_config.py
integrations/rss/requirements.txt
zulip-0.8.2.dist-info/METADATA
zulip-0.8.2.dist-info/WHEEL
zulip-0.8.2.dist-info/entry_points.txt
zulip-0.8.2.dist-info/top_level.txt
zulip-0.8.2.dist-info/RECORD
