Metadata-Version: 2.1
Name: zulip
Version: 0.8.2
Summary: Bindings for the Zulip message API
Home-page: https://www.zulip.org/
Author: Zulip Open Source Project
Author-email: zulip-devel@googlegroups.com
License: UNKNOWN
Project-URL: Source, https://github.com/zulip/python-zulip-api/
Project-URL: Documentation, https://zulip.com/api
Platform: UNKNOWN
Classifier: Development Status :: 4 - Beta
Classifier: Environment :: Web Environment
Classifier: Intended Audience :: Developers
Classifier: License :: OSI Approved :: Apache Software License
Classifier: Topic :: Communications :: Chat
Classifier: Programming Language :: Python :: 3
Classifier: Programming Language :: Python :: 3.6
Classifier: Programming Language :: Python :: 3.7
Classifier: Programming Language :: Python :: 3.8
Classifier: Programming Language :: Python :: 3.9
Requires-Python: >=3.6
